selve/__init__.py
selve/commeo.py
selve/protocol.py
selve/utils.py
python_selve_commeo-1.0.0.dist-info/METADATA
python_selve_commeo-1.0.0.dist-info/WHEEL
python_selve_commeo-1.0.0.dist-info/entry_points.txt
python_selve_commeo-1.0.0.dist-info/top_level.txt
python_selve_commeo-1.0.0.dist-info/RECORD
